EM15008UNO/__init__.py
EM15008UNO/lineales.py
EM15008UNO/no_lineales.py
em15008uno-0.1.0.dist-info/licenses/LICENSE
em15008uno-0.1.0.dist-info/METADATA
em15008uno-0.1.0.dist-info/WHEEL
em15008uno-0.1.0.dist-info/top_level.txt
em15008uno-0.1.0.dist-info/RECORD
