Metadata-Version: 2.4
Name: EM15008UNO
Version: 0.1.0
Summary: Librería para resolver sistemas de ecuaciones lineales y no lineales
Author: Héctor Echegoyen Montano
Author-email: Héctor Echegoyen Montano <em15008@ues.edu.sv>
License: MIT
Project-URL: Homepage, https://pypi.org/project/EM15008UNO/
Classifier: Programming Language :: Python :: 3
Classifier: License :: OSI Approved :: MIT License
Classifier: Operating System :: OS Independent
Requires-Python: >=3.7
License-File: LICENSE
Dynamic: author
Dynamic: license-file
